yogendra_fizzbuzz/__init__.py
yogendra_fizzbuzz-0.4.0.dist-info/entry_points.txt
yogendra_fizzbuzz-0.4.0.dist-info/WHEEL
yogendra_fizzbuzz-0.4.0.dist-info/METADATA
yogendra_fizzbuzz-0.4.0.dist-info/RECORD
