Metadata-Version: 2.1
Name: yogendra-fizzbuzz
Version: 0.4.0
Summary: Simple Fizz Buzz Game
Author: Yogendra Rampuria (Yogi)
Author-email: yogendrarampuria@gmail.com
Requires-Python: >=3.9,<4.0
Classifier: Programming Language :: Python :: 3
Classifier: Programming Language :: Python :: 3.9
Requires-Dist: homepage
Requires-Dist: keywords
Requires-Dist: keywords
Requires-Dist: license
Requires-Dist: repository
Project-URL: Issue Tracker, https://github.com/yogendra/pypi-yogendra_fizbuzz/issues
